Assignment1/Assignment-1:Q4-8-3-bit-Priority-Encoder/A1Q4_priority_encoder_8_3.v
/*
INPUT: y0 - y7
OUTPUT: q0 - q2
The Truth Table:
<-----------INPUT------------>      <-OUTPUT->
MSB>>>>>>>>>>>>>>>>>>>>>>>>>LSB     MSB>>>>>LSB

y7	y6	y5	y4	y3	y2	y1	y0      q2	q1	q0
1	0	0	0	0	0	0	0	    1	1	1
x	1	0	0	0	0	0	0	    1	1	0
x	x	1	0	0	0	0	0	    1	0	1
x	x	x	1	0	0	0	0	    1	0	0
x	x	x	x	1	0	0	0	    0	1	1
x	x	x	x	x	1	0	0	    0	1	0
x	x	x	x	x	x	1	0	    0	0	1
x	x	x	x	x	x	x	1	    0	0	0
*/

module priority_encoder_8_3(q, y);
output reg [2:0] q;
input [7:0] y;
always #5
begin
    if(y[0] == 1'b1)
    begin
        assign q = 3'b000;
    end 
    else if (y[1] == 1'b1)
    begin
        assign q = 3'b001;
    end
    else if (y[2] == 1'b1)
    begin
        assign q = 3'b010;
    end
    else if (y[3] == 1'b1)
    begin
        assign q = 3'b011;
    end
    else if (y[4] == 1'b1)
    begin
        assign q = 3'b100;
    end
    else if (y[5] == 1'b1)
    begin
        assign q = 3'b101;
    end
    else if (y[6] == 1'b1)
    begin
        assign q = 3'b110;
    end
    else if (y[7] == 1'b1)
    begin
        assign q = 3'b111;
    end
    else
    begin
        assign q = 3'bxxx;
    end       
end
endmodule

Assignment1/Assignment-1:Q4-8-3-bit-Priority-Encoder/A1Q4_priority_encoder_8_3_tb.v
`timescale 1ns/1ns
`include "q4.v"
module priority_encoder_8_3_tb;
    wire [2:0] q;
    reg [7:0] y;
    priority_encoder_8_3 uut (.q(q), .y(y));

    initial
    begin
        $dumpfile("q4_tb.vcd");
        $dumpvars(0, priority_encoder_8_3_tb);
        y=8'b11111111;
        #5;
        y=8'b11011101;
        #5;
        y=8'b01100110;
        #5;
        y=8'b00110100; 
        #5;
        y=8'b00101000;
        #5;
        y=8'b10110000;
        #5;
        y=8'b10100000;
        #5;
        y=8'b11000000;
        #5;
        y=8'b10000000;
        #5;
        y=8'b00000000;
        #10;//otherwise the output for the last case won't be visible 
        $finish; 
    end 
endmodule

Assignment1/Assignment-1:Q4-8-3-bit-Priority-Encoder/A1Q4_priority_encoder_8_3_tb.vcd
$date
	Sun Jan 23 20:56:08 2022
$end
$version
	Icarus Verilog
$end
$timescale
	1ns
$end
$scope module priority_encoder_8_3_tb $end
$var wire 3 ! q [2:0] $end
$var reg 8 " y [7:0] $end
$scope module uut $end
$var wire 8 # y [7:0] $end
$var reg 3 $ q [2:0] $end
$upscope $end
$upscope $end
$enddefinitions $end
#0
$dumpvars
bx $
b11111111 #
b11111111 "
bx !
$end
#5
b11011101 "
b11011101 #
b0 !
b0 $
#10
b1100110 "
b1100110 #
#15
b110100 "
b110100 #
b1 !
b1 $
#20
b101000 "
b101000 #
b10 !
b10 $
#25
b10110000 "
b10110000 #
b11 !
b11 $
#30
b10100000 "
b10100000 #
b100 !
b100 $
#35
b11000000 "
b11000000 #
b101 !
b101 $
#40
b10000000 "
b10000000 #
b110 !
b110 $
#45
b0 "
b0 #
b111 !
b111 $
#50
bx !
bx $
